{
	"backtraceGraph" : 
	{
		"commands" : 
		[
			"install"
		],
		"files" : 
		[
			"deps/glfw-3.3.6/CMakeLists.txt"
		],
		"nodes" : 
		[
			{
				"file" : 0
			},
			{
				"command" : 0,
				"file" : 0,
				"line" : 362,
				"parent" : 0
			},
			{
				"command" : 0,
				"file" : 0,
				"line" : 365,
				"parent" : 0
			},
			{
				"command" : 0,
				"file" : 0,
				"line" : 369,
				"parent" : 0
			},
			{
				"command" : 0,
				"file" : 0,
				"line" : 372,
				"parent" : 0
			}
		]
	},
	"installers" : 
	[
		{
			"backtrace" : 1,
			"component" : "Unspecified",
			"destination" : "include",
			"paths" : 
			[
				"deps/glfw-3.3.6/include/GLFW"
			],
			"type" : "directory"
		},
		{
			"backtrace" : 2,
			"component" : "Unspecified",
			"destination" : "lib/cmake/glfw3",
			"paths" : 
			[
				"cmake-build-release/deps/glfw-3.3.6/src/glfw3Config.cmake",
				"cmake-build-release/deps/glfw-3.3.6/src/glfw3ConfigVersion.cmake"
			],
			"type" : "file"
		},
		{
			"backtrace" : 3,
			"component" : "Unspecified",
			"destination" : "lib/cmake/glfw3",
			"exportName" : "glfwTargets",
			"exportTargets" : 
			[
				{
					"id" : "glfw::@f6b48e8eb810f9017742",
					"index" : 2
				}
			],
			"paths" : 
			[
				"deps/glfw-3.3.6/CMakeFiles/Export/lib/cmake/glfw3/glfw3Targets.cmake"
			],
			"type" : "export"
		},
		{
			"backtrace" : 4,
			"component" : "Unspecified",
			"destination" : "lib/pkgconfig",
			"paths" : 
			[
				"cmake-build-release/deps/glfw-3.3.6/src/glfw3.pc"
			],
			"type" : "file"
		}
	],
	"paths" : 
	{
		"build" : "deps/glfw-3.3.6",
		"source" : "deps/glfw-3.3.6"
	}
}
